{
  "default": "aidmaHyperRealism-FLUX-V0.2.safetensors",
  "available_loras": [
    {
      "file": "aidmaMJ6.1-FLUX-v0.4.safetensors",
      "name": "aidmaMJ6.1-FLUX-v0.4",
      "weight": "0.6",
      "add_prompt": "aidmaMJ6.1",
      "url": "https://civitai.com/models/646411/midjourney-v61-meets-flux-sdxl?modelVersionId=981456",
      "is_active": true
    },
    {
      "file": "aidmaImageUprader.safetensors",
      "name": "aidmaImageUprader",
      "weight": "0.4",
      "add_prompt": "aidmaimageupgrader",
      "url": "https://civitai.com/models/562866/flux-image-upgrader-detail-maximizer-contrast-fix-for-low-cfg-sdxl-sd-15",
      "is_active": true
    },
    {
      "file": "Egon_Art.safetensors",
      "name": "Egon_Art",
      "weight": "0.8",
      "add_prompt": " egonartCE_style",
      "url": "https://civitai.com/models/922134?modelVersionId=1034555",
      "is_active": true
    },
    {
      "file": "aidmaHyperRealism-FLUX-V0.2.safetensors",
      "name": "aidmaHyperRealism-FLUX-V0.2",
      "weight": "1.0",
      "add_prompt": "aidmaHyperrealism",
      "url": "https://civitai.com/models/730373?modelVersionId=894049",
      "is_active": true
    },
    {
      "file": "aidmaPsychadelicChaosWorld-FLUX-v0.1.safetensors",
      "name": "aidmaPsychadelicChaosWorld-FLUX-v0.1",
      "weight": "1.0",
      "add_prompt": "PsychadelicChaos",
      "url": "https://civitai.com/models/601245/flux-psychadelic-chaos-world-morph-sdxl",
      "is_active": true
    },
    {
      "file": "flux_dev_NeoAndeanArchitecture.safetensors",
      "name": "flux_dev_NeoAndeanArchitecture",
      "weight": "0.7",
      "add_prompt": "neo-andean architecture",
      "url": "https://civitai.com/models/941383?modelVersionId=1053882",
      "is_active": true
    },
    {
      "file": "Midjourney_imitation_FLUX.safetensors",
      "name": "Midjourney_imitation_FLUX",
      "weight": "1.0",
      "add_prompt": "Midjourney style",
      "url": "https://civitai.com/models/733710/midjourney-imitationflux",
      "is_active": true
    },
    {
      "file": "Sketch_Flux.safetensors",
      "name": "Sketch_Flux",
      "weight": "1.0",
      "add_prompt": "The sketch depicts",
      "url": "https://civitai.com/models/651715?modelVersionId=750685",
      "is_active": true
    },
    {
      "file": "MothFX.safetensors",
      "name": "MothFX",
      "weight": "1.0",
      "add_prompt": "MothFX",
      "url": "https://civitai.com/models/927597?modelVersionId=1038352",
      "is_active": true
    },
    {
      "file": "Circuit_Board_FLUX.safetensors",
      "name": "Circuit_Board_FLUX",
      "weight": "1.0",
      "add_prompt": "circuit trace",
      "url": "https://civitai.com/models/906994/circuit-board-flux",
      "is_active": true
    },
    {
      "file": "Phlux_Texture&Lighting.safetensors",
      "name": "Phlux_Texture&Lighting",
      "weight": "1.0",
      "add_prompt": "",
      "url": "https://civitai.com/models/672963/phlux-photorealism-with-style-incredible-texture-and-lighting",
      "is_active": true
    },
    {
      "file": "RPGv6-itr15.safetensors",
      "name": "RPGv6-itr15",
      "weight": "1.0",
      "add_prompt": "RPG STYLE,",
      "url": "https://civitai.com/models/647159?modelVersionId=796427",
      "is_active": true
    },
    {
      "file": "DreamyKolors_v1.safetensors",
      "name": "DreamyKolors_v1",
      "weight": "0.8",
      "add_prompt": "",
      "url": "https://civitai.com/models/739314/dreamykolors-unleash-creativity-enhance-quality",
      "is_active": true
    },
    {
      "file": "undeadmadness-warcraftstyle.safetensors",
      "name": "undeadmadness-warcraftstyle",
      "weight": "1.0",
      "add_prompt": "warcraftundeadstyle",
      "url": "https://civitai.com/models/868586/undead-madness-unleashed-world-of-warcraft-inspired-style",
      "is_active": true
    },
    {
      "file": "MetalArt01a_CE_FLUX_AIT3k.safetensors",
      "name": "MetalArt01a_CE_FLUX_AIT3k",
      "weight": "1.0",
      "add_prompt": "mtlartCE_style",
      "url": "https://civitai.com/models/925301/metal-art-ce-xl",
      "is_active": true
    },
    {
      "file": "Ultima_Flux_v1.safetensors",
      "name": "Ultima_Flux_v1",
      "weight": "0.3",
      "add_prompt": "",
      "url": "https://civitai.com/models/834435/ultima-flux",
      "is_active": true
    },
    {
      "file": "VantaGold.safetensors\n",
      "name": "VantaGold",
      "weight": "1.0",
      "add_prompt": "in the style of VNTGLD",
      "url": "https://civitai.com/models/816484/flux-lora-vantagold",
      "is_active": true
    },
    {
      "file": "boFLUX_AbstractMorph.safetensors",
      "name": "boFLUX_AbstractMorph",
      "weight": "1.0",
      "add_prompt": "bo-abstract",
      "url": "https://civitai.com/models/776859/flux-abstractmorph",
      "is_active": true
    },
    {
      "file": "boFLUX Digital Abstract.safetensors",
      "name": "boFLUX Digital Abstract",
      "weight": "1.0",
      "add_prompt": "bo-digitalabstract",
      "url": "https://civitai.com/models/939001/flux-digital-abstract",
      "is_active": true
    },
    {
      "file": "boFLUX_Bioluminescent_Dreams_v1.safetensors",
      "name": "boFLUX_Bioluminescent_Dreams_v1",
      "weight": "1.0",
      "add_prompt": "bo-bioluminescent",
      "url": "https://civitai.com/models/709663/flux-bioluminescent-dreams",
      "is_active": true
    },
    {
      "file": "The_beauty_of_realism_(FLUX).safetensors",
      "name": "The_beauty_of_realism_(FLUX)",
      "weight": "1.0",
      "add_prompt": "cinematic quality, realism, play of shadow and light",
      "url": "https://civitai.com/models/695295/the-beauty-of-realism-flux",
      "is_active": true
    },
    {
      "file": "Flux_1_Dev_LoRA_syntheticanime.safetensors",
      "name": "Flux_1_Dev_LoRA_syntheticanime",
      "weight": "1.0",
      "add_prompt": "syntheticanime",
      "url": "https://civitai.com/models/645425/flux-syntheticanime",
      "is_active": true
    },
    {
      "file": "flux-oilpainting1.3-00001.safetensors",
      "name": "flux-oilpainting1.3-00001",
      "weight": "1.0",
      "add_prompt": "",
      "url": "https://civitai.com/models/723141/flux-oil-painting",
      "is_active": true
    },
    {
      "file": "Steampunk_BioMechanical_Flux.safetensors",
      "name": "Steampunk_BioMechanical_Flux",
      "weight": "1.0",
      "add_prompt": "Biomechanical, Steampunk",
      "url": "https://huggingface.co/KurtcPhotoED/Biomechanical_Steampunk",
      "is_active": true
    },
    {
      "file": "deepfocus.safetensors",
      "name": "deepfocus",
      "weight": "1.0",
      "add_prompt": "DF",
      "url": "https://civitai.com/models/673483/deep-focus-lora",
      "is_active": true
    },
    {
      "file": "Flux.1_Turbo_Detailer.safetensors",
      "name": "Flux.1_Turbo_Detailer",
      "weight": "1.0",
      "add_prompt": "",
      "url": "https://civitai.com/models/930386/flux1-turbo-detailer",
      "is_active": true
    },
    {
      "file": "New Fantasy CoreV2.safetensors",
      "name": "New Fantasy CoreV2",
      "weight": "1.0",
      "add_prompt": "MyNewFantasy",
      "url": "https://civitai.com/models/810000?modelVersionId=1034430",
      "is_active": true
    },
    {
      "file": "Super Panavision 70 Technicolor.safetensors",
      "name": "Super Panavision 70 Technicolor",
      "weight": "1.0",
      "add_prompt": "In Super Panavision 70 Technicolor Film style ",
      "url": "https://civitai.com/models/812212?modelVersionId=931164",
      "is_active": true
    },
    {
      "file": "Impasto Oil Paint Style.safetensors",
      "name": "Impasto Oil Paint Style",
      "weight": "1.0",
      "add_prompt": "impaflux",
      "url": "https://civitai.com/models/899132/impasto-virtuoso-flux",
      "is_active": true
    },
    {
      "file": "Godward_Flux.safetensors",
      "name": "Godward_Flux",
      "weight": "1.0",
      "add_prompt": "The painting by Godward depicts",
      "url": "https://civitai.com/models/651715?modelVersionId=812674",
      "is_active": true
    },
    {
      "file": "Van_Gogh_Flux.safetensors",
      "name": "Van_Gogh_Flux",
      "weight": "1.0",
      "add_prompt": "The painting by Van Gogh depicts",
      "url": "https://civitai.com/models/651715?modelVersionId=733643",
      "is_active": true
    },
    {
      "file": "Monet_Flux.safetensors",
      "name": "Monet_Flux",
      "weight": "1.0",
      "add_prompt": "the painting by Monet",
      "url": "https://civitai.com/models/651715?modelVersionId=729105",
      "is_active": true
    },
    {
      "file": "Mucha_Flux.safetensors",
      "name": "Mucha_Flux",
      "weight": "1.0",
      "add_prompt": "The painting by Mucha depicts",
      "url": "https://civitai.com/models/651715?modelVersionId=738708",
      "is_active": true
    },
    {
      "file": "E_B_Leighton_Flux_resize.safetensors",
      "name": "E_B_Leighton_Flux_resize",
      "weight": "1.0",
      "add_prompt": "Lghtn",
      "url": "https://civitai.com/models/651715?modelVersionId=826858",
      "is_active": true
    },
    {
      "file": "Caravaggio_Flux.safetensors",
      "name": "Caravaggio_Flux",
      "weight": "1.0",
      "add_prompt": "The painting by Caravaggio depicts",
      "url": "https://civitai.com/models/651715?modelVersionId=742188",
      "is_active": true
    },
    {
      "file": "flux_vividizer.safetensors",
      "name": "flux_vividizer",
      "weight": "0.6",
      "add_prompt": "",
      "url": "https://civitai.com/models/663742?modelVersionId=742813",
      "is_active": true
    },
    {
      "file": "Bougeureau_Flux.safetensors",
      "name": "Bougeureau_Flux",
      "weight": "1.0",
      "add_prompt": "The painting by bougeureau depicts",
      "url": "https://civitai.com/models/651715?modelVersionId=746449",
      "is_active": true
    },
    {
      "file": "Enjolras_Flux_2.safetensors",
      "name": "Enjolras_Flux_2",
      "weight": "1.0",
      "add_prompt": "The painting by Enjolras depicts",
      "url": "https://civitai.com/models/651715?modelVersionId=754822",
      "is_active": true
    },
    {
      "file": "Chaplin_Flux.safetensors",
      "name": "Chaplin_Flux",
      "weight": "1.0",
      "add_prompt": "The painting by Chaplin depicts",
      "url": "https://civitai.com/models/651715?modelVersionId=754822",
      "is_active": true
    },
    {
      "file": "Seignac_Flux.safetensors",
      "name": "Seignac_Flux",
      "weight": "1.0",
      "add_prompt": "by Sgnc",
      "url": "https://civitai.com/models/651715?modelVersionId=775426",
      "is_active": true
    },
    {
      "file": "Cabanel_Flux.safetensors",
      "name": "Cabanel_Flux",
      "weight": "1.0",
      "add_prompt": "The painting by Cabanel depicts",
      "url": "https://civitai.com/models/651715?modelVersionId=783639",
      "is_active": true
    },
    {
      "file": "Rubens_Flux.safetensors",
      "name": "Rubens_Flux",
      "weight": "1.0",
      "add_prompt": "a painting by Rbns",
      "url": "https://civitai.com/models/651715?modelVersionId=790504",
      "is_active": true
    },
    {
      "file": "Henner_Flux.safetensors",
      "name": "Henner_Flux",
      "weight": "1.0",
      "add_prompt": "by Hnnr",
      "url": "https://civitai.com/models/651715?modelVersionId=798353",
      "is_active": true
    },
    {
      "file": "Lautrec_Flux.safetensors",
      "name": "Lautrec_Flux",
      "weight": "1.0",
      "add_prompt": "The art by Ltrc depicts ",
      "url": "https://civitai.com/models/651715?modelVersionId=805351",
      "is_active": true
    },
    {
      "file": "Rebecca Guay [Style] Flux.safetensors",
      "name": "Rebecca Guay [Style] Flux",
      "weight": "1.0",
      "add_prompt": "r3b3cc4gu4y",
      "url": "https://civitai.com/models/928101/rebecca-guay-style-flux",
      "is_active": true
    },
    {
      "file": "aidmaFLUXpro1.1-FLUX-V0.2.safetensors",
      "name": "aidmaFLUXpro1.1-FLUX-V0.2",
      "weight": "1.0",
      "add_prompt": "aidmafluxpro1.1",
      "url": "https://civitai.com/models/832683/flux-pro-11-style-lora-extreme-detailer-for-flux1-dev",
      "is_active": true
    },
    {
      "file": "Aura Flux 2.0.safetensors",
      "name": "Aura Flux 2.0",
      "weight": "1.0",
      "add_prompt": "auralora",
      "url": "https://civitai.com/models/600793?modelVersionId=925656",
      "is_active": true
    },
    {
      "file": "Textimprover-FLUX-V0.4.safetensors",
      "name": "aidma Textimprover",
      "weight": "0.6",
      "add_prompt": "aidmatextimprover",
      "url": "https://civitai.com/models/793052/text-improver-flux",
      "is_active": true
    },
    {
      "file": "aidmaPonyStyle-FLUX-V0.1.safetensors",
      "name": "aidmaPonyStyle-SFW",
      "weight": "1.0",
      "add_prompt": "aidmaponystyle",
      "url": "https://civitai.com/models/721586/pony-style-sfw-flux",
      "is_active": true
    },
    {
      "file": "aidmaNijiAnimeStyle.safetensors",
      "name": "aidmaNijiAnimeStyle",
      "weight": "0.4",
      "add_prompt": "aidmanijiv6",
      "url": "https://civitai.com/models/488923/niji-anime-style-niji-v6-midjourney-fluxsdxl",
      "is_active": true
    },
    {
      "file": "aidmaExperimentalPhotography-FLUX-V0.1.safetensors",
      "name": "aidmaExperimentalPhotography-FLUX-V0.1",
      "weight": "1.0",
      "add_prompt": "aidmaExperimentalPhotography",
      "url": "https://civitai.com/models/727417/experimental-photography-flux",
      "is_active": true
    },
    {
      "file": "aidmaDarkFantasy-FLUX-V0.1.safetensors",
      "name": "aidmaDarkFantasy-FLUX-V0.1",
      "weight": "1.0",
      "add_prompt": "aidmaDarkfantasy",
      "url": "https://civitai.com/models/753466/dark-fantasy-style-flux-training-comparison-rapid-and-normal",
      "is_active": true
    },
    {
      "file": "FluxDFaeTasticDetails.safetensors",
      "name": "FluxDFaeTasticDetails",
      "weight": "1.0",
      "add_prompt": "",
      "url": "https://civitai.com/models/643886/flux-faetastic-details",
      "is_active": true
    },
    {
      "file": "fantasy-flux-v1.safetensors",
      "name": "fantasy-flux-v1",
      "weight": "1.0",
      "add_prompt": "",
      "url": "https://civitai.com/models/714852?modelVersionId=1031155",
      "is_active": true
    },
    {
      "file": "MysticSplash.safetensors",
      "name": "MysticSplash",
      "weight": "1.0",
      "add_prompt": "MysticSplash",
      "url": "https://civitai.com/models/853829?modelVersionId=955591",
      "is_active": true
    },
    {
      "file": "vision_realistic_flux_lora_v2.safetensors",
      "name": "vision_realistic_flux_lora_v2",
      "weight": "0.8",
      "add_prompt": "",
      "url": "https://civitai.com/models/648905?modelVersionId=871696",
      "is_active": true
    },
    {
      "file": "Art Nouveau architecture.safetensors",
      "name": "Art Nouveau architecture",
      "weight": "1.0",
      "add_prompt": "ArtNvArkt",
      "url": "https://civitai.com/models/950418/art-nouveau-architecture?modelVersionId=1064079",
      "is_active": true
    }
  ]
}